claude_agent_framework/__init__.py
claude_agent_framework/cli.py
claude_agent_framework/session.py
claude_agent_framework/architectures/__init__.py
claude_agent_framework/architectures/critic_actor/__init__.py
claude_agent_framework/architectures/critic_actor/config.py
claude_agent_framework/architectures/critic_actor/orchestrator.py
claude_agent_framework/architectures/critic_actor/prompts/actor.txt
claude_agent_framework/architectures/critic_actor/prompts/critic.txt
claude_agent_framework/architectures/critic_actor/prompts/lead_agent.txt
claude_agent_framework/architectures/debate/__init__.py
claude_agent_framework/architectures/debate/config.py
claude_agent_framework/architectures/debate/orchestrator.py
claude_agent_framework/architectures/debate/prompts/judge.txt
claude_agent_framework/architectures/debate/prompts/lead_agent.txt
claude_agent_framework/architectures/debate/prompts/opponent.txt
claude_agent_framework/architectures/debate/prompts/proponent.txt
claude_agent_framework/architectures/mapreduce/__init__.py
claude_agent_framework/architectures/mapreduce/config.py
claude_agent_framework/architectures/mapreduce/orchestrator.py
claude_agent_framework/architectures/mapreduce/splitter.py
claude_agent_framework/architectures/mapreduce/prompts/lead_agent.txt
claude_agent_framework/architectures/mapreduce/prompts/mapper.txt
claude_agent_framework/architectures/mapreduce/prompts/reducer.txt
claude_agent_framework/architectures/pipeline/__init__.py
claude_agent_framework/architectures/pipeline/config.py
claude_agent_framework/architectures/pipeline/orchestrator.py
claude_agent_framework/architectures/pipeline/prompts/architect.txt
claude_agent_framework/architectures/pipeline/prompts/coder.txt
claude_agent_framework/architectures/pipeline/prompts/lead_agent.txt
claude_agent_framework/architectures/pipeline/prompts/reviewer.txt
claude_agent_framework/architectures/pipeline/prompts/stage.txt
claude_agent_framework/architectures/pipeline/prompts/tester.txt
claude_agent_framework-0.5.0.dist-info/METADATA
claude_agent_framework-0.5.0.dist-info/WHEEL
claude_agent_framework-0.5.0.dist-info/entry_points.txt
claude_agent_framework-0.5.0.dist-info/RECORD
