Metadata-Version: 2.4
Name: claude-agent-framework
Version: 0.5.0
Summary: A production-ready multi-agent orchestration framework built on Claude Agent SDK. Design, compose, and deploy complex AI workflows with pre-built architecture patterns.
Project-URL: Homepage, https://github.com/uukuguy/claude-agent-framework
Project-URL: Documentation, https://github.com/uukuguy/claude-agent-framework#readme
Project-URL: Repository, https://github.com/uukuguy/claude-agent-framework
Project-URL: Issues, https://github.com/uukuguy/claude-agent-framework/issues
Author-email: Jiangwen Su <uukuguy@gmail.com>
License: MIT
Keywords: agent,ai,architecture,claude,framework,multi-agent,research,sdk
Classifier: Development Status :: 3 - Alpha
Classifier: Intended Audience :: Developers
Classifier: License :: OSI Approved :: MIT License
Classifier: Programming Language :: Python :: 3
Classifier: Programming Language :: Python :: 3.10
Classifier: Programming Language :: Python :: 3.11
Classifier: Programming Language :: Python :: 3.12
Classifier: Topic :: Scientific/Engineering :: Artificial Intelligence
Classifier: Topic :: Software Development :: Libraries :: Python Modules
Requires-Python: >=3.10
Requires-Dist: claude-agent-sdk>=0.1.0
Requires-Dist: python-dotenv>=1.0.0
Provides-Extra: all
Requires-Dist: build>=0.10.0; extra == 'all'
Requires-Dist: jinja2>=3.1.0; extra == 'all'
Requires-Dist: matplotlib>=3.7.0; extra == 'all'
Requires-Dist: mkdocs-material>=9.0.0; extra == 'all'
Requires-Dist: mkdocs>=1.5.0; extra == 'all'
Requires-Dist: mypy>=1.0.0; extra == 'all'
Requires-Dist: pandas>=2.0.0; extra == 'all'
Requires-Dist: pdfplumber>=0.10.0; extra == 'all'
Requires-Dist: pydantic<3.0.0,>=2.0.0; extra == 'all'
Requires-Dist: pypdf>=3.0.0; extra == 'all'
Requires-Dist: pytest-asyncio>=0.21.0; extra == 'all'
Requires-Dist: pytest-cov>=4.0.0; extra == 'all'
Requires-Dist: pytest>=7.0.0; extra == 'all'
Requires-Dist: pyyaml>=6.0.0; extra == 'all'
Requires-Dist: reportlab>=4.0.0; extra == 'all'
Requires-Dist: ruff>=0.1.0; extra == 'all'
Requires-Dist: twine>=4.0.0; extra == 'all'
Provides-Extra: charts
Requires-Dist: matplotlib>=3.7.0; extra == 'charts'
Requires-Dist: pandas>=2.0.0; extra == 'charts'
Provides-Extra: config
Requires-Dist: pydantic<3.0.0,>=2.0.0; extra == 'config'
Requires-Dist: pyyaml>=6.0.0; extra == 'config'
Provides-Extra: dev
Requires-Dist: build>=0.10.0; extra == 'dev'
Requires-Dist: mypy>=1.0.0; extra == 'dev'
Requires-Dist: pytest-asyncio>=0.21.0; extra == 'dev'
Requires-Dist: pytest-cov>=4.0.0; extra == 'dev'
Requires-Dist: pytest>=7.0.0; extra == 'dev'
Requires-Dist: ruff>=0.1.0; extra == 'dev'
Requires-Dist: twine>=4.0.0; extra == 'dev'
Provides-Extra: docs
Requires-Dist: mkdocs-material>=9.0.0; extra == 'docs'
Requires-Dist: mkdocs>=1.5.0; extra == 'docs'
Provides-Extra: observability
Requires-Dist: jinja2>=3.1.0; extra == 'observability'
Provides-Extra: pdf
Requires-Dist: pdfplumber>=0.10.0; extra == 'pdf'
Requires-Dist: pypdf>=3.0.0; extra == 'pdf'
Requires-Dist: reportlab>=4.0.0; extra == 'pdf'
